LICENSE
README.md
setup.py
trademaster410/__init__.py
trademaster410.egg-info/PKG-INFO
trademaster410.egg-info/SOURCES.txt
trademaster410.egg-info/dependency_links.txt
trademaster410.egg-info/top_level.txt
trademaster410/agents/__init__.py
trademaster410/agents/builder.py
trademaster410/agents/custom.py
trademaster410/agents/algorithmic_trading/__init__.py
trademaster410/agents/algorithmic_trading/dqn.py
trademaster410/agents/high_frequency_trading/__init__.py
trademaster410/agents/high_frequency_trading/ddqn.py
trademaster410/agents/order_execution/__init__.py
trademaster410/agents/order_execution/eteo.py
trademaster410/agents/order_execution/pd.py
trademaster410/agents/portfolio_management/__init__.py
trademaster410/agents/portfolio_management/deeptrader.py
trademaster410/agents/portfolio_management/eiie.py
trademaster410/agents/portfolio_management/investor_imitator.py
trademaster410/collector/__init__.py
trademaster410/collector/binance.py
trademaster410/collector/builder.py
trademaster410/collector/custom.py
trademaster410/collector/helper/__init__.py
trademaster410/collector/helper/celery_app.py
trademaster410/collector/helper/celery_config.py
trademaster410/collector/helper/pika_connection.py
trademaster410/collector/helper/run_celery.py
trademaster410/collector/helper/websocket_consumer.py
trademaster410/collector/helper/websocket_producer.py
trademaster410/datasets/__init__.py
trademaster410/datasets/builder.py
trademaster410/datasets/custom.py
trademaster410/datasets/algorithmic_trading/__init__.py
trademaster410/datasets/algorithmic_trading/dataset.py
trademaster410/datasets/high_frequency_trading/__init__.py
trademaster410/datasets/high_frequency_trading/dataset.py
trademaster410/datasets/order_execution/__init__.py
trademaster410/datasets/order_execution/dataset.py
trademaster410/datasets/portfolio_management/__init__.py
trademaster410/datasets/portfolio_management/dataset.py
trademaster410/environments/__init__.py
trademaster410/environments/builder.py
trademaster410/environments/custom.py
trademaster410/environments/algorithmic_trading/__init__.py
